aiotaskpool/__init__.py
aiotaskpool/__version__.py
aiotaskpool-0.1.1.dist-info/LICENSE
aiotaskpool-0.1.1.dist-info/METADATA
aiotaskpool-0.1.1.dist-info/WHEEL
aiotaskpool-0.1.1.dist-info/top_level.txt
aiotaskpool-0.1.1.dist-info/RECORD
