Metadata-Version: 2.1
Name: aiotaskpool
Version: 0.1.1
Summary: aiotaskpool
Home-page: https://zeroguard.com
Author: ZeroGuard
Author-email: oss@zeroguard.com
License: AGPL-3.0
Project-URL: Source, https://github.com/zeroguard/aiotaskpool
Platform: UNKNOWN
Classifier: Development Status :: 1 - Planning
Classifier: Intended Audience :: Developers
Classifier: License :: OSI Approved :: GNU Affero General Public License v3
Classifier: Natural Language :: English
Classifier: Programming Language :: Python :: 3.7
Classifier: Programming Language :: Python :: 3.8
Classifier: Topic :: Security
Requires-Python: >=3.7
